{
  "id": "royalportrushdunlucelinks",
  "name": "Royal Portrush Dunluce Links",
  "fullName": "Royal Portrush Dunluce Links",
  "type": "standard",
  "elevation": 0,
  "video": null,
  "sku": null,
  "buyCourseDescription": "Set along Northern Ireland's breathtaking coastline, Royal Portrush's Dunluce Links is a pure links challenge. With dramatic dunes, rolling fairways, and ever-changing winds, it delivers an unforgettable golfing experience.",
  "price": null,
  "onSaleFrom": null,
  "isFirm": true,
  "additionalCourses": null,
  "courseTile": "images/courses/tiles/royalportrushdunlucelinks.avif",
  "courseImage": "images/courses/overview/royalportrushdunlucelinks.avif",
  "courseBuyImage": "images/courses/overview/royalportrushdunlucelinks.avif",
  "courseLogo": null,
  "holes": [
    {
      "hole": 1,
      "par": 4,
      "pinCoordinates": {
        "easy": [609.221, 18.173, 141.216],
        "medium": [601.221, 18.009, 140.558],
        "hard": [611.734, 18.266, 137.801]
      },
      "teeCoordinates": {
        "front": [322.287, 11.288, 235.806],
        "middle": [279.493, 12.679, 257.462],
        "back": [244.223, 12.752, 268.635]
      }
    },
    {
      "hole": 2,
      "par": 5,
      "pinCoordinates": {
        "easy": [1035.404, 20.852, 245.761],
        "medium": [1017.475, 20.485, 236.893],
        "hard": [1027.289, 20.504, 236.243]
      },
      "teeCoordinates": {
        "front": [609.688, 20.037, 105.997],
        "middle": [584.7, 19.471, 85.855],
        "back": [544.976, 19.121, 92.509]
      }
    },
    {
      "hole": 3,
      "par": 3,
      "pinCoordinates": {
        "easy": [1224.269, 29.098, 341.023],
        "medium": [1232.203, 29.229, 332.942],
        "hard": [1219.588, 29.228, 333.529]
      },
      "teeCoordinates": {
        "front": [1137.672, 29.798, 266.839],
        "middle": [1120.087, 30.25, 254.224],
        "back": [1102.694, 30.449, 243.903]
      }
    },
    {
      "hole": 4,
      "par": 4,
      "pinCoordinates": {
        "easy": [1534.218, 24.527, 610.652],
        "medium": [1532.466, 24.586, 603.805],
        "hard": [1540.934, 24.643, 611.228]
      },
      "teeCoordinates": {
        "front": [1267.817, 27.468, 343.062],
        "middle": [1209.905, 26.241, 374.483],
        "back": [1166.797, 26.669, 345.174]
      }
    },
    {
      "hole": 5,
      "par": 4,
      "pinCoordinates": {
        "easy": [1561.204, 15.632, 922.77],
        "medium": [1569.485, 15.469, 932.186],
        "hard": [1562.652, 15.45, 934.845]
      },
      "teeCoordinates": {
        "front": [1549.19, 25.142, 646.018],
        "middle": [1569.477, 27.925, 622.596],
        "back": [1574.277, 28.08, 604.896]
      }
    },
    {
      "hole": 6,
      "par": 3,
      "pinCoordinates": {
        "easy": [1405.829, 16.642, 825.74],
        "medium": [1404.428, 16.742, 817.16],
        "hard": [1416.418, 16.47, 828.391]
      },
      "teeCoordinates": {
        "front": [1503.61, 15.166, 925.798],
        "middle": [1513.11, 15.635, 934.498],
        "back": [1524.85, 15.565, 948.248]
      }
    },
    {
      "hole": 7,
      "par": 5,
      "pinCoordinates": {
        "easy": [911.704, 9.188, 978.093],
        "medium": [903.983, 9.267, 984.749],
        "hard": [914.911, 9.045, 983.574]
      },
      "teeCoordinates": {
        "front": [1324.583, 9.905, 903.023],
        "middle": [1382.883, 10.655, 905.023],
        "back": [1455.982, 13.252, 911.823]
      }
    },
    {
      "hole": 8,
      "par": 4,
      "pinCoordinates": {
        "easy": [1325.521, 15.044, 830.412],
        "medium": [1328.032, 14.971, 824.061],
        "hard": [1338.718, 15.329, 819.953]
      },
      "teeCoordinates": {
        "front": [1056.178, 11.579, 881.157],
        "middle": [1007.678, 11.46, 900.057],
        "back": [966.178, 11.476, 932.157]
      }
    },
    {
      "hole": 9,
      "par": 4,
      "pinCoordinates": {
        "easy": [1158.102, 18.542, 468.045],
        "medium": [1162.292, 18.77, 459.603],
        "hard": [1150.643, 18.801, 458.047]
      },
      "teeCoordinates": {
        "front": [1349.683, 17.383, 726.947],
        "middle": [1376.383, 16.848, 754.247],
        "back": [1384.583, 17.308, 771.247]
      }
    },
    {
      "hole": 10,
      "par": 4,
      "pinCoordinates": {
        "easy": [1308.848, 17.565, 777.857],
        "medium": [1312.531, 17.59, 773.981],
        "hard": [1329.41, 17.986, 779.635]
      },
      "teeCoordinates": {
        "front": [1142.192, 16.06, 570.184],
        "middle": [1148.342, 15.933, 543.254],
        "back": [1133.696, 15.986, 514.607]
      }
    },
    {
      "hole": 11,
      "par": 5,
      "pinCoordinates": {
        "easy": [1213.563, 19.792, 447.145],
        "medium": [1207.786, 19.922, 438.937],
        "hard": [1218.522, 19.874, 441.967]
      },
      "teeCoordinates": {
        "front": [1436.649, 18.314, 738.71],
        "middle": [1441.849, 18.013, 756.01],
        "back": [1456.149, 18.021, 783.11]
      }
    },
    {
      "hole": 12,
      "par": 5,
      "pinCoordinates": {
        "easy": [782.913, 17.608, 204.074],
        "medium": [788.441, 17.513, 199.754],
        "hard": [789.618, 17.327, 208.507]
      },
      "teeCoordinates": {
        "front": [1145.363, -176.363, 391.602],
        "middle": [1119.763, -176.363, 451.502],
        "back": [1217.963, -176.363, 414.602]
      }
    },
    {
      "hole": 13,
      "par": 3,
      "pinCoordinates": {
        "easy": [773.123, 11.903, 325.389],
        "medium": [773.862, 12.105, 313.74],
        "hard": [765.04, 12.19, 313.668]
      },
      "teeCoordinates": {
        "front": [743.924, 19.716, 194.088],
        "middle": [730.424, 20.955, 174.588],
        "back": [695.624, 21.748, 160.588]
      }
    },
    {
      "hole": 14,
      "par": 4,
      "pinCoordinates": {
        "easy": [1098.271, 16.006, 495.615],
        "medium": [1101.488, 16.249, 507.034],
        "hard": [1107.254, 16.296, 505.683]
      },
      "teeCoordinates": {
        "front": [838.673, 15.089, 297.479],
        "middle": [806.673, 16.749, 269.779],
        "back": [769.173, 16.826, 239.479]
      }
    },
    {
      "hole": 15,
      "par": 4,
      "pinCoordinates": {
        "easy": [1028.868, 16.409, 834.365],
        "medium": [1024.486, 16.308, 827.86],
        "hard": [1024.379, 16.429, 841.863]
      },
      "teeCoordinates": {
        "front": [1050.819, 14.864, 506.819],
        "middle": [1043.119, 14.886, 494.119],
        "back": [1012.319, 15.39, 465.919]
      }
    },
    {
      "hole": 16,
      "par": 3,
      "pinCoordinates": {
        "easy": [877.088, 21.259, 678.723],
        "medium": [867.012, 21.271, 682.469],
        "hard": [860.812, 21.52, 677.334]
      },
      "teeCoordinates": {
        "front": [983.723, 18.64, 784.457],
        "middle": [987.5, 16.92, 827.685],
        "back": [997.965, 17.327, 854.602]
      }
    },
    {
      "hole": 17,
      "par": 4,
      "pinCoordinates": {
        "easy": [800.006, 11.929, 367.189],
        "medium": [787.31, 11.874, 353.45],
        "hard": [791.806, 11.87, 363.982]
      },
      "teeCoordinates": {
        "front": [892.229, 21.976, 588.236],
        "middle": [916.129, 23.443, 640.136],
        "back": [962.229, 24.885, 692.136]
      }
    },
    {
      "hole": 18,
      "par": 4,
      "pinCoordinates": {
        "easy": [432.156, 12.12, 306.786],
        "medium": [426.785, 12.09, 296.817],
        "hard": [414.23, 12.054, 296.173]
      },
      "teeCoordinates": {
        "front": [729.793, 15.152, 394.284],
        "middle": [775.993, 16.059, 423.684],
        "back": [796.793, 20.195, 467.784]
      }
    }
  ]
}
